CONTRIBUTING.md
LICENSE
MANIFEST.in
MODULE.bazel
README.md
pyproject.toml
setup.py
beam/__init__.py
beam/arrayrecordio.py
beam/demo.py
beam/dofns.py
beam/example.py
beam/options.py
beam/pipelines.py
beam/testdata.py
beam/examples/example_full_demo_cli.sh
beam/examples/example_gcs_conversion.py
beam/examples/example_sink_conversion.py
beam/examples/requirements.txt
docs/Makefile
docs/README.md
docs/beam_integration.md
docs/beam_reference.rst
docs/build_docs.py
docs/changelog.md
docs/conf.py
docs/contributing.md
docs/core_concepts.md
docs/cpp_reference.rst
docs/examples.md
docs/index.rst
docs/installation.md
docs/performance.md
docs/python_reference.rst
docs/quickstart.md
docs/requirements.txt
python/__init__.py
python/array_record_data_source.py
python/array_record_data_source_test.py
python/array_record_module_test.py
python/testdata/BUILD
python/testdata/digits.array_record-00000-of-00002
python/testdata/digits.array_record-00001-of-00002