Metadata-Version: 2.1
Name: array-record-python
Version: 0.8.1
Summary: A high-performance file format for ML data storage with parallel I/O and random access
Home-page: https://github.com/bzantium/array_record
Author: ArrayRecord Python Contributors
Author-email: bzantium@users.noreply.github.com
License: Apache-2.0
Project-URL: Documentation, https://arrayrecord.readthedocs.io
Project-URL: Bug Reports, https://github.com/bzantium/array_record/issues
Project-URL: Source, https://github.com/bzantium/array_record
Keywords: machine-learning,data-storage,parallel-io,compression,tensorflow,jax
Platform: UNKNOWN
Classifier: Development Status :: 4 - Beta
Classifier: Intended Audience :: Developers
Classifier: Intended Audience :: Science/Research
Classifier: License :: OSI Approved :: Apache Software License
Classifier: Programming Language :: Python :: 3
Classifier: Programming Language :: Python :: 3.10
Classifier: Programming Language :: Python :: 3.11
Classifier: Programming Language :: Python :: 3.12
Classifier: Programming Language :: Python :: 3.13
Classifier: Programming Language :: C++
Classifier: Topic :: Scientific/Engineering :: Artificial Intelligence
Classifier: Topic :: Software Development :: Libraries :: Python Modules
Classifier: Topic :: System :: Archiving :: Compression
Classifier: Operating System :: POSIX :: Linux
Classifier: Operating System :: MacOS
Requires-Python: >=3.10
Provides-Extra: beam
Provides-Extra: test
License-File: LICENSE
